labelcls/__init__.py
labelcls/run.py
labelcls/app/__init__.py
labelcls/app/presenter/__init__.py
labelcls/app/presenter/classification_presenter.py
labelcls/view/favicon.ico
labelcls/view/css/app.css
labelcls/view/css/libs/materialize.css
labelcls/view/css/libs/materialize.min.css
labelcls/view/html/classification.html
labelcls/view/js/classification.js
labelcls/view/js/components/app_header.js
labelcls/view/js/components/filelist.js
labelcls/view/js/components/image_canvas.js
labelcls/view/js/components/sidebar.js
labelcls/view/js/components/toolbox.js
labelcls/view/js/components/util_components.js
labelcls/view/js/components/labels/label_form.js
labelcls/view/js/components/labels/label_item.js
labelcls/view/js/components/labels/labelbox.js
labelcls/view/js/libs/jquery-3.5.1.min.js
labelcls/view/js/libs/materialize.js
labelcls/view/js/libs/materialize.min.js
labelcls/view/js/libs/vue.js
labelcls/view/js/libs/vue.min.js
labelcls-1.1.6.dist-info/LICENSE
labelcls-1.1.6.dist-info/METADATA
labelcls-1.1.6.dist-info/WHEEL
labelcls-1.1.6.dist-info/entry_points.txt
labelcls-1.1.6.dist-info/top_level.txt
labelcls-1.1.6.dist-info/RECORD
