Metadata-Version: 2.1
Name: labelcls
Version: 1.1.6
Summary: Annotation tool of image classification data.
Home-page: https://github.com/pei223/labelcls
Author: pei223
Author-email: peidparc@gmail.com
License: MIT
Keywords: image-classification annotation annotation-tool
Platform: UNKNOWN
Classifier: License :: OSI Approved :: MIT License
Classifier: Programming Language :: Python :: 3.7
Requires-Dist: eel
Requires-Dist: Pillow
